<?xml version="1.0" encoding="UTF-8"?>
<!DOCTYPE mapper PUBLIC "-//mybatis.org//DTD Mapper 3.0//EN" "http://mybatis.org/dtd/mybatis-3-mapper.dtd">
<mapper namespace="ext.datasource.inf.SUserMapper">
  <resultMap id="BaseResultMap" type="ext.datasource.entity.SUser">
    <!--
      WARNING - @mbg.generated
      This element is automatically generated by MyBatis Generator, do not modify.
      This element was generated on Thu Jun 15 20:37:45 GMT+08:00 2017.
    -->
    <id column="ID" jdbcType="INTEGER" property="id" />
    <result column="USER_NAME" jdbcType="VARCHAR" property="userName" />
    <result column="USER_PWD" jdbcType="VARCHAR" property="userPwd" />
    <result column="CREATE_DATE" jdbcType="DATE" property="createDate" />
    <result column="UPDATE_DAATE" jdbcType="DATE" property="updateDaate" />
    <result column="OWN_USER" jdbcType="INTEGER" property="ownUser" />
    <result column="USER_TYPE" jdbcType="INTEGER" property="userType" />
  </resultMap>
  <sql id="Example_Where_Clause">
    <!--
      WARNING - @mbg.generated
      This element is automatically generated by MyBatis Generator, do not modify.
      This element was generated on Thu Jun 15 20:37:45 GMT+08:00 2017.
    -->
    <where>
      <foreach collection="oredCriteria" item="criteria" separator="or">
        <if test="criteria.valid">
          <trim prefix="(" prefixOverrides="and" suffix=")">
            <foreach collection="criteria.criteria" item="criterion">
              <choose>
                <when test="criterion.noValue">
                  and ${criterion.condition}
                </when>
                <when test="criterion.singleValue">
                  and ${criterion.condition} #{criterion.value}
                </when>
                <when test="criterion.betweenValue">
                  and ${criterion.condition} #{criterion.value} and #{criterion.secondValue}
                </when>
                <when test="criterion.listValue">
                  and ${criterion.condition}
                  <foreach close=")" collection="criterion.value" item="listItem" open="(" separator=",">
                    #{listItem}
                  </foreach>
                </when>
              </choose>
            </foreach>
          </trim>
        </if>
      </foreach>
    </where>
  </sql>
  <sql id="Update_By_Example_Where_Clause">
    <!--
      WARNING - @mbg.generated
      This element is automatically generated by MyBatis Generator, do not modify.
      This element was generated on Thu Jun 15 20:37:45 GMT+08:00 2017.
    -->
    <where>
      <foreach collection="example.oredCriteria" item="criteria" separator="or">
        <if test="criteria.valid">
          <trim prefix="(" prefixOverrides="and" suffix=")">
            <foreach collection="criteria.criteria" item="criterion">
              <choose>
                <when test="criterion.noValue">
                  and ${criterion.condition}
                </when>
                <when test="criterion.singleValue">
                  and ${criterion.condition} #{criterion.value}
                </when>
                <when test="criterion.betweenValue">
                  and ${criterion.condition} #{criterion.value} and #{criterion.secondValue}
                </when>
                <when test="criterion.listValue">
                  and ${criterion.condition}
                  <foreach close=")" collection="criterion.value" item="listItem" open="(" separator=",">
                    #{listItem}
                  </foreach>
                </when>
              </choose>
            </foreach>
          </trim>
        </if>
      </foreach>
    </where>
  </sql>
  <sql id="Base_Column_List">
    <!--
      WARNING - @mbg.generated
      This element is automatically generated by MyBatis Generator, do not modify.
      This element was generated on Thu Jun 15 20:37:45 GMT+08:00 2017.
    -->
    ID, USER_NAME, USER_PWD, CREATE_DATE, UPDATE_DAATE, OWN_USER, USER_TYPE
  </sql>
  <select id="selectByExample" parameterType="ext.datasource.entity.SUserExample" resultMap="BaseResultMap">
    <!--
      WARNING - @mbg.generated
      This element is automatically generated by MyBatis Generator, do not modify.
      This element was generated on Thu Jun 15 20:37:45 GMT+08:00 2017.
    -->
    select
    <if test="distinct">
      distinct
    </if>
    <include refid="Base_Column_List" />
    from S_USER
    <if test="_parameter != null">
      <include refid="Example_Where_Clause" />
    </if>
    <if test="orderByClause != null">
      order by ${orderByClause}
    </if>
  </select>
  <select id="selectByPrimaryKey" parameterType="java.lang.Integer" resultMap="BaseResultMap">
    <!--
      WARNING - @mbg.generated
      This element is automatically generated by MyBatis Generator, do not modify.
      This element was generated on Thu Jun 15 20:37:45 GMT+08:00 2017.
    -->
    select 
    <include refid="Base_Column_List" />
    from S_USER
    where ID = #{id,jdbcType=INTEGER}
  </select>
  <delete id="deleteByPrimaryKey" parameterType="java.lang.Integer">
    <!--
      WARNING - @mbg.generated
      This element is automatically generated by MyBatis Generator, do not modify.
      This element was generated on Thu Jun 15 20:37:45 GMT+08:00 2017.
    -->
    delete from S_USER
    where ID = #{id,jdbcType=INTEGER}
  </delete>
  <delete id="deleteByExample" parameterType="ext.datasource.entity.SUserExample">
    <!--
      WARNING - @mbg.generated
      This element is automatically generated by MyBatis Generator, do not modify.
      This element was generated on Thu Jun 15 20:37:45 GMT+08:00 2017.
    -->
    delete from S_USER
    <if test="_parameter != null">
      <include refid="Example_Where_Clause" />
    </if>
  </delete>
  <insert id="insert" parameterType="ext.datasource.entity.SUser">
    <!--
      WARNING - @mbg.generated
      This element is automatically generated by MyBatis Generator, do not modify.
      This element was generated on Thu Jun 15 20:37:45 GMT+08:00 2017.
    -->
    insert into S_USER (ID, USER_NAME, USER_PWD, 
      CREATE_DATE, UPDATE_DAATE, OWN_USER, 
      USER_TYPE)
    values (#{id,jdbcType=INTEGER}, #{userName,jdbcType=VARCHAR}, #{userPwd,jdbcType=VARCHAR}, 
      #{createDate,jdbcType=DATE}, #{updateDaate,jdbcType=DATE}, #{ownUser,jdbcType=INTEGER}, 
      #{userType,jdbcType=INTEGER})
  </insert>
  <insert id="insertSelective" parameterType="ext.datasource.entity.SUser">
    <!--
      WARNING - @mbg.generated
      This element is automatically generated by MyBatis Generator, do not modify.
      This element was generated on Thu Jun 15 20:37:45 GMT+08:00 2017.
    -->
    insert into S_USER
    <trim prefix="(" suffix=")" suffixOverrides=",">
      <if test="id != null">
        ID,
      </if>
      <if test="userName != null">
        USER_NAME,
      </if>
      <if test="userPwd != null">
        USER_PWD,
      </if>
      <if test="createDate != null">
        CREATE_DATE,
      </if>
      <if test="updateDaate != null">
        UPDATE_DAATE,
      </if>
      <if test="ownUser != null">
        OWN_USER,
      </if>
      <if test="userType != null">
        USER_TYPE,
      </if>
    </trim>
    <trim prefix="values (" suffix=")" suffixOverrides=",">
      <if test="id != null">
        #{id,jdbcType=INTEGER},
      </if>
      <if test="userName != null">
        #{userName,jdbcType=VARCHAR},
      </if>
      <if test="userPwd != null">
        #{userPwd,jdbcType=VARCHAR},
      </if>
      <if test="createDate != null">
        #{createDate,jdbcType=DATE},
      </if>
      <if test="updateDaate != null">
        #{updateDaate,jdbcType=DATE},
      </if>
      <if test="ownUser != null">
        #{ownUser,jdbcType=INTEGER},
      </if>
      <if test="userType != null">
        #{userType,jdbcType=INTEGER},
      </if>
    </trim>
  </insert>
  <select id="countByExample" parameterType="ext.datasource.entity.SUserExample" resultType="java.lang.Long">
    <!--
      WARNING - @mbg.generated
      This element is automatically generated by MyBatis Generator, do not modify.
      This element was generated on Thu Jun 15 20:37:45 GMT+08:00 2017.
    -->
    select count(*) from S_USER
    <if test="_parameter != null">
      <include refid="Example_Where_Clause" />
    </if>
  </select>
  <update id="updateByExampleSelective" parameterType="map">
    <!--
      WARNING - @mbg.generated
      This element is automatically generated by MyBatis Generator, do not modify.
      This element was generated on Thu Jun 15 20:37:45 GMT+08:00 2017.
    -->
    update S_USER
    <set>
      <if test="record.id != null">
        ID = #{record.id,jdbcType=INTEGER},
      </if>
      <if test="record.userName != null">
        USER_NAME = #{record.userName,jdbcType=VARCHAR},
      </if>
      <if test="record.userPwd != null">
        USER_PWD = #{record.userPwd,jdbcType=VARCHAR},
      </if>
      <if test="record.createDate != null">
        CREATE_DATE = #{record.createDate,jdbcType=DATE},
      </if>
      <if test="record.updateDaate != null">
        UPDATE_DAATE = #{record.updateDaate,jdbcType=DATE},
      </if>
      <if test="record.ownUser != null">
        OWN_USER = #{record.ownUser,jdbcType=INTEGER},
      </if>
      <if test="record.userType != null">
        USER_TYPE = #{record.userType,jdbcType=INTEGER},
      </if>
    </set>
    <if test="_parameter != null">
      <include refid="Update_By_Example_Where_Clause" />
    </if>
  </update>
  <update id="updateByExample" parameterType="map">
    <!--
      WARNING - @mbg.generated
      This element is automatically generated by MyBatis Generator, do not modify.
      This element was generated on Thu Jun 15 20:37:45 GMT+08:00 2017.
    -->
    update S_USER
    set ID = #{record.id,jdbcType=INTEGER},
      USER_NAME = #{record.userName,jdbcType=VARCHAR},
      USER_PWD = #{record.userPwd,jdbcType=VARCHAR},
      CREATE_DATE = #{record.createDate,jdbcType=DATE},
      UPDATE_DAATE = #{record.updateDaate,jdbcType=DATE},
      OWN_USER = #{record.ownUser,jdbcType=INTEGER},
      USER_TYPE = #{record.userType,jdbcType=INTEGER}
    <if test="_parameter != null">
      <include refid="Update_By_Example_Where_Clause" />
    </if>
  </update>
  <update id="updateByPrimaryKeySelective" parameterType="ext.datasource.entity.SUser">
    <!--
      WARNING - @mbg.generated
      This element is automatically generated by MyBatis Generator, do not modify.
      This element was generated on Thu Jun 15 20:37:45 GMT+08:00 2017.
    -->
    update S_USER
    <set>
      <if test="userName != null">
        USER_NAME = #{userName,jdbcType=VARCHAR},
      </if>
      <if test="userPwd != null">
        USER_PWD = #{userPwd,jdbcType=VARCHAR},
      </if>
      <if test="createDate != null">
        CREATE_DATE = #{createDate,jdbcType=DATE},
      </if>
      <if test="updateDaate != null">
        UPDATE_DAATE = #{updateDaate,jdbcType=DATE},
      </if>
      <if test="ownUser != null">
        OWN_USER = #{ownUser,jdbcType=INTEGER},
      </if>
      <if test="userType != null">
        USER_TYPE = #{userType,jdbcType=INTEGER},
      </if>
    </set>
    where ID = #{id,jdbcType=INTEGER}
  </update>
  <update id="updateByPrimaryKey" parameterType="ext.datasource.entity.SUser">
    <!--
      WARNING - @mbg.generated
      This element is automatically generated by MyBatis Generator, do not modify.
      This element was generated on Thu Jun 15 20:37:45 GMT+08:00 2017.
    -->
    update S_USER
    set USER_NAME = #{userName,jdbcType=VARCHAR},
      USER_PWD = #{userPwd,jdbcType=VARCHAR},
      CREATE_DATE = #{createDate,jdbcType=DATE},
      UPDATE_DAATE = #{updateDaate,jdbcType=DATE},
      OWN_USER = #{ownUser,jdbcType=INTEGER},
      USER_TYPE = #{userType,jdbcType=INTEGER}
    where ID = #{id,jdbcType=INTEGER}
  </update>
  
  <select id="getUser" resultMap="BaseResultMap">
  select	
   <include refid="Base_Column_List" />
    from S_USER
    where USER_NAME=#{0} AND USER_PWD=#{1}
  </select>
</mapper>